django_cooco/__init__.py
django_cooco/admin.py
django_cooco/apps.py
django_cooco/migrations/0001_initial.py
django_cooco/migrations/__init__.py
django_cooco/models.py
django_cooco/py.typed
django_cooco/templatetags/__init__.py
django_cooco/templatetags/cooco.py
django_cooco/urls.py
django_cooco/utils.py
django_cooco/views.py
django_cooco-0.0.1.dist-info/LICENSE.md
django_cooco-0.0.1.dist-info/METADATA
django_cooco-0.0.1.dist-info/WHEEL
django_cooco-0.0.1.dist-info/RECORD
